bot.py
upload.py
src/firefish/__init__.py
src/firefish/firefish.py
firefish_py-0.0.2.dist-info/METADATA
firefish_py-0.0.2.dist-info/WHEEL
firefish_py-0.0.2.dist-info/licenses/LICENSE
firefish_py-0.0.2.dist-info/RECORD
