Metadata-Version: 2.1
Name: firefish.py
Version: 0.0.2
Summary: A python wrapper for firefish/calckey
Project-URL: Homepage, https://codeberg.org/phin/firefish.py
Project-URL: Bug Tracker, https://codeberg.org/phin/firefish.py/issues
Author-email: phin <phinw@protonmail.com>
License-File: LICENSE
Classifier: License :: OSI Approved :: The Unlicense (Unlicense)
Classifier: Operating System :: OS Independent
Classifier: Programming Language :: Python :: 3
Requires-Python: >=3
